ll/la/__init__.py
ll/la/handlers.py
ll_la-0.54.0.dist-info/licenses/LICENSE.txt
ll_la-0.54.0.dist-info/METADATA
ll_la-0.54.0.dist-info/WHEEL
ll_la-0.54.0.dist-info/top_level.txt
ll_la-0.54.0.dist-info/RECORD
