Metadata-Version: 2.4
Name: ll-la
Version: 0.54.0
Summary: Python API for LivingApps
Home-page: http://github.com/LivingLogic/LivingApps.Python.LivingAPI
Author: Walter Doerwald
Author-email: walter@livinglogic.de
License: MIT
Keywords: LivingApps
Classifier: Development Status :: 5 - Production/Stable
Classifier: Intended Audience :: Developers
Classifier: License :: OSI Approved :: MIT License
Classifier: Operating System :: OS Independent
Classifier: Programming Language :: Python
Classifier: Programming Language :: Python :: 3
Classifier: Programming Language :: Python :: 3 :: Only
Classifier: Programming Language :: Python :: 3.14
Classifier: Topic :: Internet :: WWW/HTTP
Classifier: Topic :: Software Development :: Libraries :: Python Modules
Requires-Python: >=3.14
License-File: LICENSE.txt
Requires-Dist: ll-xist>=5.82.1
Requires-Dist: requests>=2.21.0
Requires-Dist: geocoder>=1.30.1
Requires-Dist: Pillow>=6.1.0
Requires-Dist: validators>=0.18.2
Provides-Extra: db
Requires-Dist: oracledb; extra == "db"
Requires-Dist: psycopg[binary]>=3.0.5; extra == "db"
Dynamic: author
Dynamic: author-email
Dynamic: classifier
Dynamic: description
Dynamic: home-page
Dynamic: keywords
Dynamic: license
Dynamic: license-file
Dynamic: provides-extra
Dynamic: requires-dist
Dynamic: requires-python
Dynamic: summary
